Weka355YonghuZhinan/README.md
Weka355YonghuZhinan/__init__.py
Weka355YonghuZhinan/__main__.py
Weka355YonghuZhinan/file.epub
Weka355YonghuZhinan/index.html
Weka355YonghuZhinan/css/__init__.py
Weka355YonghuZhinan/css/annotations.css
Weka355YonghuZhinan/css/main.css
Weka355YonghuZhinan/css/normalize.css
Weka355YonghuZhinan/css/popup.css
Weka355YonghuZhinan/font/__init__.py
Weka355YonghuZhinan/font/fontello.eot
Weka355YonghuZhinan/font/fontello.svg
Weka355YonghuZhinan/font/fontello.ttf
Weka355YonghuZhinan/font/fontello.woff
Weka355YonghuZhinan/img/__init__.py
Weka355YonghuZhinan/img/annotator-glyph-sprite.png
Weka355YonghuZhinan/img/annotator-icon-sprite.png
Weka355YonghuZhinan/img/apple-touch-icon.png
Weka355YonghuZhinan/img/cancelfullscreen.png
Weka355YonghuZhinan/img/close.png
Weka355YonghuZhinan/img/fullscreen.png
Weka355YonghuZhinan/img/loader.gif
Weka355YonghuZhinan/img/menu-icon.png
Weka355YonghuZhinan/img/save.png
Weka355YonghuZhinan/img/saved.png
Weka355YonghuZhinan/img/settings-s.png
Weka355YonghuZhinan/img/settings.png
Weka355YonghuZhinan/img/star.png
Weka355YonghuZhinan/js/__init__.py
Weka355YonghuZhinan/js/epub.js
Weka355YonghuZhinan/js/epub.min.js
Weka355YonghuZhinan/js/epub.min.map
Weka355YonghuZhinan/js/hooks.min.js
Weka355YonghuZhinan/js/hooks.min.map
Weka355YonghuZhinan/js/reader.js
Weka355YonghuZhinan/js/reader.js.map
Weka355YonghuZhinan/js/reader.min.js
Weka355YonghuZhinan/js/reader.min.map
Weka355YonghuZhinan/js/hooks/__init__.py
Weka355YonghuZhinan/js/hooks/extensions/__init__.py
Weka355YonghuZhinan/js/hooks/extensions/highlight.js
Weka355YonghuZhinan/js/libs/__init__.py
Weka355YonghuZhinan/js/libs/jquery.min.js
Weka355YonghuZhinan/js/libs/localforage.min.js
Weka355YonghuZhinan/js/libs/screenfull.js
Weka355YonghuZhinan/js/libs/screenfull.min.js
Weka355YonghuZhinan/js/libs/zip.min.js
Weka355YonghuZhinan/js/plugins/__init__.py
Weka355YonghuZhinan/js/plugins/hypothesis.js
Weka355YonghuZhinan/js/plugins/search.js
weka_3_5_5_yonghu_zhinan-2024.3.2.0.dist-info/METADATA
weka_3_5_5_yonghu_zhinan-2024.3.2.0.dist-info/WHEEL
weka_3_5_5_yonghu_zhinan-2024.3.2.0.dist-info/entry_points.txt
weka_3_5_5_yonghu_zhinan-2024.3.2.0.dist-info/top_level.txt
weka_3_5_5_yonghu_zhinan-2024.3.2.0.dist-info/RECORD
